pyxi_kafka_client/__init__.py
pyxi_kafka_client/configuration_builder.py
pyxi_kafka_client/kafka_consumer_manager.py
pyxi_kafka_client/kafka_producer_manager.py
pyxi_kafka_client/secret_provider.py
pyxi_kafka_client-0.0.6.dist-info/LICENSE
pyxi_kafka_client-0.0.6.dist-info/METADATA
pyxi_kafka_client-0.0.6.dist-info/WHEEL
pyxi_kafka_client-0.0.6.dist-info/top_level.txt
pyxi_kafka_client-0.0.6.dist-info/RECORD
