Metadata-Version: 2.1
Name: pyxi-kafka-client
Version: 0.0.6
Summary: A basic kafka client for python.
Home-page: https://github.com/stiproot/py-kafka-client
Author: Simon Stipcich
Author-email: stipcich.simon@gmail.com
License: MIT
Keywords: python,package,kafka,beta
Classifier: Intended Audience :: Developers
Classifier: License :: OSI Approved :: MIT License
Classifier: Programming Language :: Python :: 3.11
License-File: LICENSE
Requires-Dist: environs
Requires-Dist: confluent-kafka
